swh/graph/libs/__init__.py
swh/graph/libs/py.typed
swh/graph/libs/shell.py
swh/graph/libs/luigi/__init__.py
swh/graph/libs/luigi/topology.py
swh/graph/libs/tests/__init__.py
swh/graph/libs/tests/test_swh_graph_libs.py
swh/graph/libs/tests/luigi/__init__.py
swh/graph/libs/tests/luigi/test_topology.py
swh_graph_libs-10.1.0.dist-info/licenses/AUTHORS
swh_graph_libs-10.1.0.dist-info/licenses/LICENSE
swh_graph_libs-10.1.0.dist-info/METADATA
swh_graph_libs-10.1.0.dist-info/WHEEL
swh_graph_libs-10.1.0.dist-info/top_level.txt
swh_graph_libs-10.1.0.dist-info/RECORD
